pubmed_downloader/__init__.py
pubmed_downloader/__main__.py
pubmed_downloader/api.py
pubmed_downloader/catalog.py
pubmed_downloader/cli.py
pubmed_downloader/client.py
pubmed_downloader/py.typed
pubmed_downloader/utils.py
pubmed_downloader/version.py
pubmed_downloader-0.0.12.dist-info/licenses/LICENSE
pubmed_downloader-0.0.12.dist-info/WHEEL
pubmed_downloader-0.0.12.dist-info/entry_points.txt
pubmed_downloader-0.0.12.dist-info/METADATA
pubmed_downloader-0.0.12.dist-info/RECORD
