Metadata-Version: 2.4
Name: pubmed-downloader
Version: 0.0.12
Summary: Automate downloading and processing PubMed
Keywords: snekpack,cookiecutter,PubMed,MEDLINE,biomedical literature
Author: Charles Tapley Hoyt
Author-email: Charles Tapley Hoyt <cthoyt@gmail.com>
License-File: LICENSE
Classifier: Development Status :: 1 - Planning
Classifier: Environment :: Console
Classifier: Intended Audience :: Developers
Classifier: License :: OSI Approved :: MIT License
Classifier: Operating System :: OS Independent
Classifier: Framework :: Pytest
Classifier: Framework :: tox
Classifier: Framework :: Sphinx
Classifier: Natural Language :: English
Classifier: Programming Language :: Python
Classifier: Programming Language :: Python :: 3.10
Classifier: Programming Language :: Python :: 3.11
Classifier: Programming Language :: Python :: 3.12
Classifier: Programming Language :: Python :: 3.13
Classifier: Programming Language :: Python :: 3 :: Only
Classifier: Typing :: Typed
Requires-Dist: tqdm
Requires-Dist: click
Requires-Dist: requests
Requires-Dist: beautifulsoup4
Requires-Dist: pystow
Requires-Dist: pydantic
Requires-Dist: pydantic-extra-types
Requires-Dist: lxml
Requires-Dist: curies>=0.10.6
Requires-Dist: ssslm>=0.0.12
Requires-Dist: typing-extensions
Requires-Dist: more-itertools
Requires-Dist: ratelimit
Requires-Dist: pyobo ; extra == 'process'
Maintainer: Charles Tapley Hoyt
Maintainer-email: Charles Tapley Hoyt <cthoyt@gmail.com>
Requires-Python: >=3.10
Project-URL: Bug Tracker, https://github.com/cthoyt/pubmed-downloader/issues
Project-URL: Documentation, https://pubmed_downloader.readthedocs.io
Project-URL: Funding, https://github.com/sponsors/cthoyt
Project-URL: Homepage, https://github.com/cthoyt/pubmed-downloader
Project-URL: Repository, https://github.com/cthoyt/pubmed-downloader.git
Provides-Extra: process
